reghdfe/__init__.py
reghdfe/api.py
reghdfe/core.py
reghdfe/covariance.py
reghdfe/hdfe.py
reghdfe/results.py
reghdfe-0.1.1.dist-info/licenses/LICENSE
reghdfe-0.1.1.dist-info/METADATA
reghdfe-0.1.1.dist-info/WHEEL
reghdfe-0.1.1.dist-info/top_level.txt
reghdfe-0.1.1.dist-info/RECORD
