Metadata-Version: 2.4
Name: reghdfe
Version: 0.1.1
Summary: Python implementation of Stata's reghdfe for high-dimensional fixed effects regression
Author: RegHDFE Contributors
Maintainer: RegHDFE Contributors
License-Expression: MIT
Project-URL: Homepage, https://github.com/brycewang-stanford/reghdfe
Project-URL: Documentation, https://github.com/brycewang-stanford/reghdfe#documentation
Project-URL: Repository, https://github.com/brycewang-stanford/reghdfe.git
Project-URL: Bug Tracker, https://github.com/brycewang-stanford/reghdfe/issues
Keywords: econometrics,fixed-effects,regression,hdfe,panel-data
Classifier: Development Status :: 4 - Beta
Classifier: Intended Audience :: Science/Research
Classifier: Operating System :: OS Independent
Classifier: Programming Language :: Python :: 3
Classifier: Programming Language :: Python :: 3.9
Classifier: Programming Language :: Python :: 3.10
Classifier: Programming Language :: Python :: 3.11
Classifier: Programming Language :: Python :: 3.12
Classifier: Programming Language :: Python :: 3.13
Classifier: Topic :: Scientific/Engineering
Classifier: Topic :: Scientific/Engineering :: Information Analysis
Requires-Python: >=3.9
License-File: LICENSE
Requires-Dist: numpy>=1.20.0
Requires-Dist: scipy>=1.7.0
Requires-Dist: pandas>=1.3.0
Requires-Dist: pyhdfe>=0.1.0
Requires-Dist: tabulate>=0.8.0
Provides-Extra: dev
Requires-Dist: pytest>=6.0; extra == "dev"
Requires-Dist: pytest-cov>=2.0; extra == "dev"
Requires-Dist: ruff>=0.1.0; extra == "dev"
Requires-Dist: mypy>=1.0; extra == "dev"
Requires-Dist: pandas-stubs; extra == "dev"
Provides-Extra: docs
Requires-Dist: sphinx>=4.0; extra == "docs"
Requires-Dist: sphinx-rtd-theme; extra == "docs"
Requires-Dist: numpydoc; extra == "docs"
Dynamic: license-file
